[{"id":"13794509861","type":"PushEvent","actor":{"id":154518586,"login":"ayupandey12","display_login":"ayupandey12","gravatar_id":"","url":"https://api.github.com/users/ayupandey12","avatar_url":"https://avatars.githubusercontent.com/u/154518586?"},"repo":{"id":1271812652,"name":"ayupandey12/Task-tracker-cli-app","url":"https://api.github.com/repos/ayupandey12/Task-tracker-cli-app"},"payload":{"repository_id":1271812652,"push_id":36082589787,"ref":"refs/heads/main","head":"3f6635dd01771be098b5358780402bd8e39e6470","before":"47b91d71bd1dd5fe20a4aed281f8ae893464129b"},"public":true,"created_at":"2026-06-24T03:38:37Z"},{"id":"13794086107","type":"PushEvent","actor":{"id":154518586,"login":"ayupandey12","display_login":"ayupandey12","gravatar_id":"","url":"https://api.github.com/users/ayupandey12","avatar_url":"https://avatars.githubusercontent.com/u/154518586?"},"repo":{"id":1271812652,"name":"ayupandey12/Task-tracker-cli-app","url":"https://api.github.com/repos/ayupandey12/Task-tracker-cli-app"},"payload":{"repository_id":1271812652,"push_id":36082165705,"ref":"refs/heads/main","head":"47b91d71bd1dd5fe20a4aed281f8ae893464129b","before":"9d6cc6b4a17dd5d27da5f7f90a40661d03db5e25"},"public":true,"created_at":"2026-06-24T03:24:13Z"},{"id":"13794027455","type":"PushEvent","actor":{"id":154518586,"login":"ayupandey12","display_login":"ayupandey12","gravatar_id":"","url":"https://api.github.com/users/ayupandey12","avatar_url":"https://avatars.githubusercontent.com/u/154518586?"},"repo":{"id":1271812652,"name":"ayupandey12/Task-tracker-cli-app","url":"https://api.github.com/repos/ayupandey12/Task-tracker-cli-app"},"payload":{"repository_id":1271812652,"push_id":36082107054,"ref":"refs/heads/main","head":"9d6cc6b4a17dd5d27da5f7f90a40661d03db5e25","before":"6d3144c8f4b5a6473ed4c81d7b6e496df22641ad"},"public":true,"created_at":"2026-06-24T03:22:10Z"},{"id":"13793947251","type":"PushEvent","actor":{"id":154518586,"login":"ayupandey12","display_login":"ayupandey12","gravatar_id":"","url":"https://api.github.com/users/ayupandey12","avatar_url":"https://avatars.githubusercontent.com/u/154518586?"},"repo":{"id":1271812652,"name":"ayupandey12/Task-tracker-cli-app","url":"https://api.github.com/repos/ayupandey12/Task-tracker-cli-app"},"payload":{"repository_id":1271812652,"push_id":36082026795,"ref":"refs/heads/main","head":"6d3144c8f4b5a6473ed4c81d7b6e496df22641ad","before":"d20676dd92521e49327c355f23d4f1884d46e69f"},"public":true,"created_at":"2026-06-24T03:19:22Z"},{"id":"13793888501","type":"PushEvent","actor":{"id":154518586,"login":"ayupandey12","display_login":"ayupandey12","gravatar_id":"","url":"https://api.github.com/users/ayupandey12","avatar_url":"https://avatars.githubusercontent.com/u/154518586?"},"repo":{"id":1271812652,"name":"ayupandey12/Task-tracker-cli-app","url":"https://api.github.com/repos/ayupandey12/Task-tracker-cli-app"},"payload":{"repository_id":1271812652,"push_id":36081967898,"ref":"refs/heads/main","head":"d20676dd92521e49327c355f23d4f1884d46e69f","before":"36a6c4b90e08cd38f5b3e0498facbe558c6cb58e"},"public":true,"created_at":"2026-06-24T03:17:22Z"},{"id":"13793687146","type":"PushEvent","actor":{"id":154518586,"login":"ayupandey12","display_login":"ayupandey12","gravatar_id":"","url":"https://api.github.com/users/ayupandey12","avatar_url":"https://avatars.githubusercontent.com/u/154518586?"},"repo":{"id":1271812652,"name":"ayupandey12/Task-tracker-cli-app","url":"https://api.github.com/repos/ayupandey12/Task-tracker-cli-app"},"payload":{"repository_id":1271812652,"push_id":36081766063,"ref":"refs/heads/main","head":"36a6c4b90e08cd38f5b3e0498facbe558c6cb58e","before":"6ce348d0ccabf54bffb1202d556aa3ba7ec12d9c"},"public":true,"created_at":"2026-06-24T03:10:25Z"},{"id":"13793617493","type":"PushEvent","actor":{"id":154518586,"login":"ayupandey12","display_login":"ayupandey12","gravatar_id":"","url":"https://api.github.com/users/ayupandey12","avatar_url":"https://avatars.githubusercontent.com/u/154518586?"},"repo":{"id":1271812652,"name":"ayupandey12/Task-tracker-cli-app","url":"https://api.github.com/repos/ayupandey12/Task-tracker-cli-app"},"payload":{"repository_id":1271812652,"push_id":36081696144,"ref":"refs/heads/main","head":"6ce348d0ccabf54bffb1202d556aa3ba7ec12d9c","before":"7818a7e5aa0041ae2f965fb8dd83bea4e6b559a9"},"public":true,"created_at":"2026-06-24T03:07:59Z"},{"id":"13738037213","type":"CreateEvent","actor":{"id":154518586,"login":"ayupandey12","display_login":"ayupandey12","gravatar_id":"","url":"https://api.github.com/users/ayupandey12","avatar_url":"https://avatars.githubusercontent.com/u/154518586?"},"repo":{"id":1277650798,"name":"ayupandey12/YCjob-fetcher","url":"https://api.github.com/repos/ayupandey12/YCjob-fetcher"},"payload":{"ref":"main","ref_type":"branch","full_ref":"refs/heads/main","master_branch":"main","description":null,"pusher_type":"user"},"public":true,"created_at":"2026-06-23T04:50:31Z"},{"id":"13676383935","type":"PushEvent","actor":{"id":154518586,"login":"ayupandey12","display_login":"ayupandey12","gravatar_id":"","url":"https://api.github.com/users/ayupandey12","avatar_url":"https://avatars.githubusercontent.com/u/154518586?"},"repo":{"id":1269046490,"name":"ayupandey12/react-machine-coding","url":"https://api.github.com/repos/ayupandey12/react-machine-coding"},"payload":{"repository_id":1269046490,"push_id":35964585481,"ref":"refs/heads/main","head":"7d8deef2b2c453c7a5d9e729a1593563f717fde1","before":"49321e8ab21da4dfb6e50804586749297f96d16f"},"public":true,"created_at":"2026-06-22T03:16:37Z"},{"id":"13648842883","type":"PushEvent","actor":{"id":154518586,"login":"ayupandey12","display_login":"ayupandey12","gravatar_id":"","url":"https://api.github.com/users/ayupandey12","avatar_url":"https://avatars.githubusercontent.com/u/154518586?"},"repo":{"id":1271812652,"name":"ayupandey12/Task-tracker-cli-app","url":"https://api.github.com/repos/ayupandey12/Task-tracker-cli-app"},"payload":{"repository_id":1271812652,"push_id":35937004613,"ref":"refs/heads/main","head":"7818a7e5aa0041ae2f965fb8dd83bea4e6b559a9","before":"d5de8b0daac9c49f99e2d71c18bca970be3fe96a"},"public":true,"created_at":"2026-06-21T08:46:35Z"},{"id":"13622548221","type":"PushEvent","actor":{"id":154518586,"login":"ayupandey12","display_login":"ayupandey12","gravatar_id":"","url":"https://api.github.com/users/ayupandey12","avatar_url":"https://avatars.githubusercontent.com/u/154518586?"},"repo":{"id":1271812652,"name":"ayupandey12/Task-tracker-cli-app","url":"https://api.github.com/repos/ayupandey12/Task-tracker-cli-app"},"payload":{"repository_id":1271812652,"push_id":35910663849,"ref":"refs/heads/main","head":"d5de8b0daac9c49f99e2d71c18bca970be3fe96a","before":"471dfb34570b545076c9547c149a00ae8e18ab34"},"public":true,"created_at":"2026-06-20T12:59:27Z"},{"id":"13621994209","type":"PushEvent","actor":{"id":154518586,"login":"ayupandey12","display_login":"ayupandey12","gravatar_id":"","url":"https://api.github.com/users/ayupandey12","avatar_url":"https://avatars.githubusercontent.com/u/154518586?"},"repo":{"id":1271812652,"name":"ayupandey12/Task-tracker-cli-app","url":"https://api.github.com/repos/ayupandey12/Task-tracker-cli-app"},"payload":{"repository_id":1271812652,"push_id":35910108962,"ref":"refs/heads/main","head":"471dfb34570b545076c9547c149a00ae8e18ab34","before":"5787cd89fd82d9098a052d3759360f308b6be2e7"},"public":true,"created_at":"2026-06-20T12:35:47Z"},{"id":"13501257979","type":"PushEvent","actor":{"id":154518586,"login":"ayupandey12","display_login":"ayupandey12","gravatar_id":"","url":"https://api.github.com/users/ayupandey12","avatar_url":"https://avatars.githubusercontent.com/u/154518586?"},"repo":{"id":1271812652,"name":"ayupandey12/Task-tracker-cli-app","url":"https://api.github.com/repos/ayupandey12/Task-tracker-cli-app"},"payload":{"repository_id":1271812652,"push_id":35789438836,"ref":"refs/heads/main","head":"5787cd89fd82d9098a052d3759360f308b6be2e7","before":"7fb0bb272c189dad58f39e61ece8ce2acc51fe7b"},"public":true,"created_at":"2026-06-18T03:02:33Z"},{"id":"13444107860","type":"PushEvent","actor":{"id":154518586,"login":"ayupandey12","display_login":"ayupandey12","gravatar_id":"","url":"https://api.github.com/users/ayupandey12","avatar_url":"https://avatars.githubusercontent.com/u/154518586?"},"repo":{"id":1271812652,"name":"ayupandey12/Task-tracker-cli-app","url":"https://api.github.com/repos/ayupandey12/Task-tracker-cli-app"},"payload":{"repository_id":1271812652,"push_id":35732286943,"ref":"refs/heads/main","head":"7fb0bb272c189dad58f39e61ece8ce2acc51fe7b","before":"5371897f5d7da2cef3b7c72d9666fd7fc6b42d8c"},"public":true,"created_at":"2026-06-17T04:07:54Z"},{"id":"13442629078","type":"CreateEvent","actor":{"id":154518586,"login":"ayupandey12","display_login":"ayupandey12","gravatar_id":"","url":"https://api.github.com/users/ayupandey12","avatar_url":"https://avatars.githubusercontent.com/u/154518586?"},"repo":{"id":1271812652,"name":"ayupandey12/Task-tracker-cli-app","url":"https://api.github.com/repos/ayupandey12/Task-tracker-cli-app"},"payload":{"ref":"main","ref_type":"branch","full_ref":"refs/heads/main","master_branch":"main","description":null,"pusher_type":"user"},"public":true,"created_at":"2026-06-17T03:17:42Z"},{"id":"13384462828","type":"PushEvent","actor":{"id":154518586,"login":"ayupandey12","display_login":"ayupandey12","gravatar_id":"","url":"https://api.github.com/users/ayupandey12","avatar_url":"https://avatars.githubusercontent.com/u/154518586?"},"repo":{"id":1269046490,"name":"ayupandey12/react-machine-coding","url":"https://api.github.com/repos/ayupandey12/react-machine-coding"},"payload":{"repository_id":1269046490,"push_id":35672318251,"ref":"refs/heads/main","head":"49321e8ab21da4dfb6e50804586749297f96d16f","before":"9da820492556d20a2704db96e38ccb464b42873e"},"public":true,"created_at":"2026-06-16T03:34:37Z"},{"id":"13298505918","type":"CreateEvent","actor":{"id":154518586,"login":"ayupandey12","display_login":"ayupandey12","gravatar_id":"","url":"https://api.github.com/users/ayupandey12","avatar_url":"https://avatars.githubusercontent.com/u/154518586?"},"repo":{"id":1269046490,"name":"ayupandey12/react-machine-coding","url":"https://api.github.com/repos/ayupandey12/react-machine-coding"},"payload":{"ref":"main","ref_type":"branch","full_ref":"refs/heads/main","master_branch":"main","description":null,"pusher_type":"user"},"public":true,"created_at":"2026-06-14T09:12:17Z"},{"id":"12612575116","type":"PushEvent","actor":{"id":154518586,"login":"ayupandey12","display_login":"ayupandey12","gravatar_id":"","url":"https://api.github.com/users/ayupandey12","avatar_url":"https://avatars.githubusercontent.com/u/154518586?"},"repo":{"id":1243252820,"name":"ayupandey12/portfolio","url":"https://api.github.com/repos/ayupandey12/portfolio"},"payload":{"repository_id":1243252820,"push_id":34902196323,"ref":"refs/heads/main","head":"e9f8d674e30276da6921ba0b72433708804c9bea","before":"ec7b6fd27fd7643dd907f33eaee67ee8fed131fa"},"public":true,"created_at":"2026-05-31T12:58:31Z"},{"id":"12583759649","type":"PushEvent","actor":{"id":154518586,"login":"ayupandey12","display_login":"ayupandey12","gravatar_id":"","url":"https://api.github.com/users/ayupandey12","avatar_url":"https://avatars.githubusercontent.com/u/154518586?"},"repo":{"id":1243252820,"name":"ayupandey12/portfolio","url":"https://api.github.com/repos/ayupandey12/portfolio"},"payload":{"repository_id":1243252820,"push_id":34873358314,"ref":"refs/heads/main","head":"ec7b6fd27fd7643dd907f33eaee67ee8fed131fa","before":"cd41dab3d1479fc7449bf2a616ea0580feddf68c"},"public":true,"created_at":"2026-05-30T13:44:31Z"},{"id":"12583652494","type":"PushEvent","actor":{"id":154518586,"login":"ayupandey12","display_login":"ayupandey12","gravatar_id":"","url":"https://api.github.com/users/ayupandey12","avatar_url":"https://avatars.githubusercontent.com/u/154518586?"},"repo":{"id":1243252820,"name":"ayupandey12/portfolio","url":"https://api.github.com/repos/ayupandey12/portfolio"},"payload":{"repository_id":1243252820,"push_id":34873251121,"ref":"refs/heads/main","head":"cd41dab3d1479fc7449bf2a616ea0580feddf68c","before":"465ca9bf6d79f1dec1641f0e238bbccb76067f69"},"public":true,"created_at":"2026-05-30T13:39:59Z"},{"id":"12583451049","type":"PushEvent","actor":{"id":154518586,"login":"ayupandey12","display_login":"ayupandey12","gravatar_id":"","url":"https://api.github.com/users/ayupandey12","avatar_url":"https://avatars.githubusercontent.com/u/154518586?"},"repo":{"id":1243252820,"name":"ayupandey12/portfolio","url":"https://api.github.com/repos/ayupandey12/portfolio"},"payload":{"repository_id":1243252820,"push_id":34873049572,"ref":"refs/heads/main","head":"465ca9bf6d79f1dec1641f0e238bbccb76067f69","before":"135c0ca7d34f80b6e0785b75c231a0c30f57c1da"},"public":true,"created_at":"2026-05-30T13:31:23Z"},{"id":"12583307399","type":"PushEvent","actor":{"id":154518586,"login":"ayupandey12","display_login":"ayupandey12","gravatar_id":"","url":"https://api.github.com/users/ayupandey12","avatar_url":"https://avatars.githubusercontent.com/u/154518586?"},"repo":{"id":1243252820,"name":"ayupandey12/portfolio","url":"https://api.github.com/repos/ayupandey12/portfolio"},"payload":{"repository_id":1243252820,"push_id":34872906208,"ref":"refs/heads/main","head":"135c0ca7d34f80b6e0785b75c231a0c30f57c1da","before":"99919004b4faafdd2658faecc9075fde4face17b"},"public":true,"created_at":"2026-05-30T13:25:20Z"},{"id":"12583230285","type":"PushEvent","actor":{"id":154518586,"login":"ayupandey12","display_login":"ayupandey12","gravatar_id":"","url":"https://api.github.com/users/ayupandey12","avatar_url":"https://avatars.githubusercontent.com/u/154518586?"},"repo":{"id":1243252820,"name":"ayupandey12/portfolio","url":"https://api.github.com/repos/ayupandey12/portfolio"},"payload":{"repository_id":1243252820,"push_id":34872829240,"ref":"refs/heads/main","head":"99919004b4faafdd2658faecc9075fde4face17b","before":"a972733d7fae25dcb72df95a8e4e025ab4d5f1bb"},"public":true,"created_at":"2026-05-30T13:22:03Z"},{"id":"12582659043","type":"PushEvent","actor":{"id":154518586,"login":"ayupandey12","display_login":"ayupandey12","gravatar_id":"","url":"https://api.github.com/users/ayupandey12","avatar_url":"https://avatars.githubusercontent.com/u/154518586?"},"repo":{"id":1243252820,"name":"ayupandey12/portfolio","url":"https://api.github.com/repos/ayupandey12/portfolio"},"payload":{"repository_id":1243252820,"push_id":34872257694,"ref":"refs/heads/main","head":"a972733d7fae25dcb72df95a8e4e025ab4d5f1bb","before":"87845c908bf4677f7cb3568c5ca0c8c0c772bb5b"},"public":true,"created_at":"2026-05-30T12:58:16Z"}]